fabricatio_milvus/__init__.py
fabricatio_milvus/config.py
fabricatio_milvus/py.typed
fabricatio_milvus/actions/__init__.py
fabricatio_milvus/actions/rag.py
fabricatio_milvus/capabilities/__init__.py
fabricatio_milvus/capabilities/milvus.py
fabricatio_milvus/models/__init__.py
fabricatio_milvus/models/kwargs_types.py
fabricatio_milvus/models/milvus.py
fabricatio_milvus/workflows/__init__.py
tests/test_milvus.py
fabricatio_milvus-0.1.0.dist-info/METADATA
fabricatio_milvus-0.1.0.dist-info/WHEEL
fabricatio_milvus-0.1.0.dist-info/RECORD
