Metadata-Version: 2.4
Name: fabricatio-milvus
Version: 0.1.0
Summary: An extension of fabricatio
Project-URL: Homepage, https://github.com/Whth/fabricatio
Project-URL: Repository, https://github.com/Whth/fabricatio
Project-URL: Issues, https://github.com/Whth/fabricatio/issues
Author-email: Whth <zettainspector@foxmail.com>
License-Expression: MIT
Classifier: License :: OSI Approved :: MIT License
Classifier: Programming Language :: Python :: 3.12
Classifier: Programming Language :: Python :: 3.13
Classifier: Programming Language :: Python :: 3.14
Classifier: Programming Language :: Python :: Implementation :: CPython
Classifier: Typing :: Typed
Requires-Python: <3.15,>=3.12
Requires-Dist: fabricatio-core
Requires-Dist: fabricatio-rag
Requires-Dist: more-itertools>=10.8.0
Requires-Dist: pydantic>=2.7.1
Requires-Dist: pymilvus>=2.5.4
